NiukeJavaGangweiMianshiZhentiBaodian20212022Fix1/README.md
NiukeJavaGangweiMianshiZhentiBaodian20212022Fix1/__init__.py
NiukeJavaGangweiMianshiZhentiBaodian20212022Fix1/__main__.py
NiukeJavaGangweiMianshiZhentiBaodian20212022Fix1/file.epub
NiukeJavaGangweiMianshiZhentiBaodian20212022Fix1/index.html
NiukeJavaGangweiMianshiZhentiBaodian20212022Fix1/css/__init__.py
NiukeJavaGangweiMianshiZhentiBaodian20212022Fix1/css/annotations.css
NiukeJavaGangweiMianshiZhentiBaodian20212022Fix1/css/main.css
NiukeJavaGangweiMianshiZhentiBaodian20212022Fix1/css/normalize.css
NiukeJavaGangweiMianshiZhentiBaodian20212022Fix1/css/popup.css
NiukeJavaGangweiMianshiZhentiBaodian20212022Fix1/font/__init__.py
NiukeJavaGangweiMianshiZhentiBaodian20212022Fix1/font/fontello.eot
NiukeJavaGangweiMianshiZhentiBaodian20212022Fix1/font/fontello.svg
NiukeJavaGangweiMianshiZhentiBaodian20212022Fix1/font/fontello.ttf
NiukeJavaGangweiMianshiZhentiBaodian20212022Fix1/font/fontello.woff
NiukeJavaGangweiMianshiZhentiBaodian20212022Fix1/img/__init__.py
NiukeJavaGangweiMianshiZhentiBaodian20212022Fix1/img/annotator-glyph-sprite.png
NiukeJavaGangweiMianshiZhentiBaodian20212022Fix1/img/annotator-icon-sprite.png
NiukeJavaGangweiMianshiZhentiBaodian20212022Fix1/img/apple-touch-icon.png
NiukeJavaGangweiMianshiZhentiBaodian20212022Fix1/img/cancelfullscreen.png
NiukeJavaGangweiMianshiZhentiBaodian20212022Fix1/img/close.png
NiukeJavaGangweiMianshiZhentiBaodian20212022Fix1/img/fullscreen.png
NiukeJavaGangweiMianshiZhentiBaodian20212022Fix1/img/loader.gif
NiukeJavaGangweiMianshiZhentiBaodian20212022Fix1/img/menu-icon.png
NiukeJavaGangweiMianshiZhentiBaodian20212022Fix1/img/save.png
NiukeJavaGangweiMianshiZhentiBaodian20212022Fix1/img/saved.png
NiukeJavaGangweiMianshiZhentiBaodian20212022Fix1/img/settings-s.png
NiukeJavaGangweiMianshiZhentiBaodian20212022Fix1/img/settings.png
NiukeJavaGangweiMianshiZhentiBaodian20212022Fix1/img/star.png
NiukeJavaGangweiMianshiZhentiBaodian20212022Fix1/js/__init__.py
niuke_java_gangwei_mianshi_zhenti_baodian_2021_2022_fix1-2025.3.25.0.dist-info/METADATA
niuke_java_gangwei_mianshi_zhenti_baodian_2021_2022_fix1-2025.3.25.0.dist-info/WHEEL
niuke_java_gangwei_mianshi_zhenti_baodian_2021_2022_fix1-2025.3.25.0.dist-info/entry_points.txt
niuke_java_gangwei_mianshi_zhenti_baodian_2021_2022_fix1-2025.3.25.0.dist-info/top_level.txt
niuke_java_gangwei_mianshi_zhenti_baodian_2021_2022_fix1-2025.3.25.0.dist-info/RECORD
